interutils/__init__.py
interutils/config.py
interutils/fs.py
interutils/interactive.py
interutils/iteration_timer.py
interutils/net.py
interutils-0.12.7.dist-info/LICENSE
interutils-0.12.7.dist-info/METADATA
interutils-0.12.7.dist-info/WHEEL
interutils-0.12.7.dist-info/top_level.txt
interutils-0.12.7.dist-info/RECORD
