Metadata-Version: 2.1
Name: interutils
Version: 0.12.7
Summary: A collection of utilities for creating interactive console scripts
Home-page: https://github.com/codeswhite/interutils
Author: Max G
Author-email: max3227@gmail.com
License: UNKNOWN
Platform: UNKNOWN
Classifier: Programming Language :: Python :: 3
Classifier: License :: OSI Approved :: MIT License
Classifier: Operating System :: OS Independent
Requires-Python: >=3.8
Requires-Dist: termcolor
